owlsec/__init__.py
owlsec/main.py
owlsec/scripts/__init__.py
owlsec/scripts/ascii_art.py
owlsec/scripts/input_handling/__init__.py
owlsec/scripts/input_handling/input_filtering.py
owlsec/scripts/input_handling/tldlist.py
owlsec/scripts/pentesting/SSL_check.py
owlsec/scripts/pentesting/__init__.py
owlsec/scripts/pentesting/common_files.py
owlsec/scripts/pentesting/common_login_forms.py
owlsec/scripts/pentesting/common_ports.py
owlsec/scripts/pentesting/find_software.py
owlsec/scripts/pentesting/passive_subdomains.py
owlsec-0.9.dist-info/METADATA
owlsec-0.9.dist-info/WHEEL
owlsec-0.9.dist-info/entry_points.txt
owlsec-0.9.dist-info/top_level.txt
owlsec-0.9.dist-info/RECORD
