Metadata-Version: 2.1
Name: owlsec
Version: 0.9
Summary: UNKNOWN
Home-page: UNKNOWN
License: UNKNOWN
Platform: UNKNOWN
Requires-Dist: argparse (==1.4.0)
Requires-Dist: beautifulsoup4 (==4.12.2)
Requires-Dist: pyOpenSSL (==23.2.0)
Requires-Dist: requests (==2.29.0)
Requires-Dist: tldextract (==2.2.0)
Requires-Dist: urllib3 (==1.26.17)
